describer_ml/__init__.py
describer_ml/matching/__init__.py
describer_ml/matching/match.py
describer_ml/numeric/__init__.py
describer_ml/numeric/num_stats.py
describer_ml/timeseries/__init__.py
describer_ml/timeseries/timeseries.py
describer_ml/timeseries/timeseries_visualization.py
describer_ml-0.28.1.dist-info/licenses/LICENSE
describer_ml-0.28.1.dist-info/METADATA
describer_ml-0.28.1.dist-info/WHEEL
describer_ml-0.28.1.dist-info/top_level.txt
describer_ml-0.28.1.dist-info/RECORD
