Metadata-Version: 2.4
Name: describer_ml
Version: 0.28.1
Summary: A set of descriptive statistics and hypothesis tests
Home-page: https://github.com/EricSchles/describer_ml
Author: Eric Schles
Author-email: ericschles@gmail.com
License: MIT
Classifier: License :: OSI Approved :: MIT License
Classifier: Programming Language :: Python :: 3
Classifier: Programming Language :: Python :: 3.6
Classifier: Programming Language :: Python :: 3.7
License-File: LICENSE
Requires-Dist: scikit-learn
Requires-Dist: scipy
Requires-Dist: numpy
Requires-Dist: statsmodels
Requires-Dist: pytest
Requires-Dist: mlxtend
Requires-Dist: ThinkBayes2
Dynamic: author
Dynamic: author-email
Dynamic: classifier
Dynamic: description
Dynamic: description-content-type
Dynamic: home-page
Dynamic: license
Dynamic: license-file
Dynamic: requires-dist
Dynamic: summary
